ansys/api/lumerical/__init__.py
ansys/api/lumerical/lumapi.py
ansys_api_lumerical-0.1.0.dist-info/licenses/LICENSE
ansys_api_lumerical-0.1.0.dist-info/WHEEL
ansys_api_lumerical-0.1.0.dist-info/METADATA
ansys_api_lumerical-0.1.0.dist-info/RECORD
